COPYING
MANIFEST.in
README.rst
requirements.txt
setup.cfg
setup.py
deploy/admin_site
deploy/admin_site_demo
deploy/modis_admin.conf
deploy/supervisord_site
modislock.egg-info/PKG-INFO
modislock.egg-info/SOURCES.txt
modislock.egg-info/dependency_links.txt
modislock.egg-info/entry_points.txt
modislock.egg-info/not-zip-safe
modislock.egg-info/requires.txt
modislock.egg-info/top_level.txt
modislock_webservice/__init__.py
modislock_webservice/celery_worker.py
modislock_webservice/extensions.py
modislock_webservice/tasks.py
modislock_webservice/wsgi.py
modislock_webservice/config/__init__.py
modislock_webservice/config/default.py
modislock_webservice/config/demonstration.py
modislock_webservice/config/development.py
modislock_webservice/config/production.py
modislock_webservice/config/testing.py
modislock_webservice/controllers/__init__.py
modislock_webservice/controllers/help.py
modislock_webservice/controllers/index.py
modislock_webservice/controllers/logs.py
modislock_webservice/controllers/settings.py
modislock_webservice/controllers/test.py
modislock_webservice/controllers/users.py
modislock_webservice/controllers/api/__init__.py
modislock_webservice/controllers/api/decorators.py
modislock_webservice/controllers/api/event_api.py
modislock_webservice/controllers/api/key_api.py
modislock_webservice/controllers/api/users_api.py
modislock_webservice/controllers/api/utils_api.py
modislock_webservice/controllers/registration/__init__.py
modislock_webservice/controllers/registration/welcome.py
modislock_webservice/forms/__init__.py
modislock_webservice/forms/account.py
modislock_webservice/forms/settings_api.py
modislock_webservice/forms/settings_backup.py
modislock_webservice/forms/settings_email.py
modislock_webservice/forms/settings_ldap.py
modislock_webservice/forms/settings_network.py
modislock_webservice/forms/settings_rules.py
modislock_webservice/forms/settings_security.py
modislock_webservice/forms/settings_timezone.py
modislock_webservice/forms/welcome.py
modislock_webservice/macros/_form.html
modislock_webservice/macros/event/_event.html
modislock_webservice/macros/event/_event.js
modislock_webservice/macros/network_field/_network_field.html
