Metadata-Version: 1.2
Name: modislock
Version: 0.2.1
Summary: Administration web interface for Modis© Lock
Home-page: https://github.com/Modis-GmbH/ModisLock-WebAdmin
Author: Richard Lowe
Author-email: richard@modis.io
License: GPL
Keywords: modis,raspberry pi,lock,administration
Platform: Linux
Platform: Raspberry Pi
Classifier: Development Status :: 4 - Beta
Classifier: Programming Language :: Python :: 3
Classifier: Programming Language :: Python :: 3.5
Classifier: Environment :: Console
Classifier: Programming Language :: Python
Classifier: Intended Audience :: Developers
Classifier: License :: OSI Approved
Classifier: License :: OSI Approved :: GNU Lesser General Public License v3 (LGPLv3)
Classifier: Operating System :: POSIX :: Linux
Classifier: Topic :: Security
Requires-Python: >=3.5
